backend/__init__.py
frontend/__init__.py
frontend/get_account_info.py
frontend/get_book_info.py
work_with_database-0.0.1.dist-info/METADATA
work_with_database-0.0.1.dist-info/WHEEL
work_with_database-0.0.1.dist-info/top_level.txt
work_with_database-0.0.1.dist-info/RECORD
